{
	"configurations" : 
	[
		{
			"abstractTargets" : [],
			"directories" : 
			[
				{
					"build" : ".",
					"jsonFile" : "directory-.-Debug-9ad1a58d4644cf6543fa.json",
					"minimumCMakeVersion" : 
					{
						"string" : "3.16"
					},
					"projectIndex" : 0,
					"source" : ".",
					"targetIndexes" : 
					[
						0
					]
				}
			],
			"name" : "Debug",
			"projects" : 
			[
				{
					"directoryIndexes" : 
					[
						0
					],
					"name" : "terminalSnake",
					"targetIndexes" : 
					[
						0
					]
				}
			],
			"targets" : 
			[
				{
					"directoryIndex" : 0,
					"id" : "terminalSnake.out::@6890427a1f51a3e7e1df",
					"jsonFile" : "target-terminalSnake.out-Debug-a1ce2c76689a54845a20.json",
					"name" : "terminalSnake.out",
					"projectIndex" : 0
				}
			]
		}
	],
	"kind" : "codemodel",
	"paths" : 
	{
		"build" : "/home/ellis/Documents/code/c/terminalSnake/build",
		"source" : "/home/ellis/Documents/code/c/terminalSnake"
	},
	"version" : 
	{
		"major" : 2,
		"minor" : 9
	}
}
